{
    "image_path": "images/000010-rot_070.png",
    "height": 480,
    "width": 640,
    "masks": [
        {
            "label": "obj_000010",
            "points": [
                [
                    299,
                    164
                ],
                [
                    282,
                    170
                ],
                [
                    298,
                    206
                ],
                [
                    307,
                    288
                ],
                [
                    287,
                    319
                ],
                [
                    290,
                    333
                ],
                [
                    320,
                    319
                ],
                [
                    357,
                    285
                ],
                [
                    352,
                    278
                ],
                [
                    327,
                    279
                ],
                [
                    318,
                    208
                ]
            ]
        }
    ]
}