{
    "image_path": "images/000001-rot_015.png",
    "height": 480,
    "width": 640,
    "masks": [
        {
            "label": "obj_000001",
            "points": [
                [
                    288,
                    151
                ],
                [
                    287,
                    202
                ],
                [
                    333,
                    256
                ],
                [
                    291,
                    292
                ],
                [
                    295,
                    316
                ],
                [
                    346,
                    274
                ],
                [
                    363,
                    233
                ]
            ]
        }
    ]
}