{
    "image_path": "images/000008-rot_009.png",
    "height": 480,
    "width": 640,
    "masks": [
        {
            "label": "obj_000008",
            "points": [
                [
                    249,
                    208
                ],
                [
                    236,
                    245
                ],
                [
                    253,
                    264
                ],
                [
                    338,
                    296
                ],
                [
                    393,
                    295
                ],
                [
                    396,
                    278
                ],
                [
                    389,
                    271
                ],
                [
                    399,
                    269
                ],
                [
                    403,
                    249
                ],
                [
                    385,
                    232
                ],
                [
                    389,
                    204
                ],
                [
                    371,
                    186
                ],
                [
                    336,
                    172
                ],
                [
                    300,
                    170
                ],
                [
                    287,
                    177
                ],
                [
                    273,
                    203
                ],
                [
                    257,
                    200
                ]
            ]
        }
    ]
}