{
    "image_path": "images/000019-rot_094.png",
    "height": 480,
    "width": 640,
    "masks": [
        {
            "label": "obj_000019",
            "points": [
                [
                    394,
                    172
                ],
                [
                    358,
                    152
                ],
                [
                    303,
                    167
                ],
                [
                    236,
                    278
                ],
                [
                    257,
                    268
                ],
                [
                    309,
                    179
                ],
                [
                    363,
                    166
                ],
                [
                    387,
                    184
                ],
                [
                    392,
                    210
                ],
                [
                    340,
                    287
                ],
                [
                    340,
                    309
                ],
                [
                    398,
                    228
                ]
            ]
        }
    ]
}