{
    "image_path": "images/000008-rot_030.png",
    "height": 480,
    "width": 640,
    "masks": [
        {
            "label": "obj_000008",
            "points": [
                [
                    270,
                    181
                ],
                [
                    237,
                    232
                ],
                [
                    239,
                    268
                ],
                [
                    237,
                    233
                ],
                [
                    268,
                    184
                ],
                [
                    333,
                    173
                ],
                [
                    386,
                    198
                ],
                [
                    404,
                    247
                ],
                [
                    394,
                    294
                ],
                [
                    317,
                    321
                ],
                [
                    241,
                    284
                ],
                [
                    316,
                    321
                ],
                [
                    378,
                    311
                ],
                [
                    404,
                    251
                ],
                [
                    384,
                    194
                ],
                [
                    325,
                    172
                ]
            ]
        }
    ]
}