{
    "image_path": "images/000020-rot_009.png",
    "height": 480,
    "width": 640,
    "masks": [
        {
            "label": "obj_000020",
            "points": [
                [
                    283,
                    152
                ],
                [
                    269,
                    190
                ],
                [
                    275,
                    206
                ],
                [
                    314,
                    201
                ],
                [
                    344,
                    272
                ],
                [
                    312,
                    298
                ],
                [
                    323,
                    318
                ],
                [
                    346,
                    305
                ],
                [
                    343,
                    289
                ],
                [
                    381,
                    259
                ],
                [
                    340,
                    164
                ],
                [
                    295,
                    170
                ]
            ]
        }
    ]
}