{
    "image_path": "images/000004-rot_031.png",
    "height": 480,
    "width": 640,
    "masks": [
        {
            "label": "obj_000004",
            "points": [
                [
                    291,
                    303
                ],
                [
                    298,
                    303
                ],
                [
                    301,
                    305
                ],
                [
                    300,
                    306
                ],
                [
                    293,
                    306
                ],
                [
                    292,
                    305
                ],
                [
                    292,
                    306
                ],
                [
                    301,
                    306
                ],
                [
                    301,
                    304
                ],
                [
                    299,
                    304
                ],
                [
                    298,
                    303
                ]
            ]
        }
    ]
}