{
    "image_path": "images/000011-rot_039.png",
    "height": 480,
    "width": 640,
    "masks": [
        {
            "label": "obj_000011",
            "points": [
                [
                    351,
                    163
                ],
                [
                    265,
                    277
                ],
                [
                    291,
                    299
                ],
                [
                    312,
                    296
                ],
                [
                    391,
                    212
                ],
                [
                    385,
                    189
                ]
            ]
        }
    ]
}