{
    "image_path": "images/000020-rot_030.png",
    "height": 480,
    "width": 640,
    "masks": [
        {
            "label": "obj_000020",
            "points": [
                [
                    251,
                    246
                ],
                [
                    307,
                    285
                ],
                [
                    321,
                    282
                ],
                [
                    341,
                    248
                ],
                [
                    382,
                    276
                ],
                [
                    400,
                    272
                ],
                [
                    389,
                    261
                ],
                [
                    399,
                    232
                ],
                [
                    335,
                    179
                ],
                [
                    282,
                    204
                ]
            ]
        }
    ]
}