{
    "image_path": "images/000014-rot_037.png",
    "height": 480,
    "width": 640,
    "masks": [
        {
            "label": "obj_000014",
            "points": [
                [
                    236,
                    186
                ],
                [
                    231,
                    219
                ],
                [
                    252,
                    246
                ],
                [
                    349,
                    300
                ],
                [
                    371,
                    301
                ],
                [
                    392,
                    287
                ],
                [
                    397,
                    260
                ],
                [
                    389,
                    243
                ],
                [
                    297,
                    176
                ],
                [
                    264,
                    168
                ]
            ]
        }
    ]
}